cloud_array/__init__.py
cloud_array/array.py
cloud_array/backends.py
cloud_array/exceptions.py
cloud_array/helpers.py
cloud_array-0.0.7.dist-info/LICENSE
cloud_array-0.0.7.dist-info/METADATA
cloud_array-0.0.7.dist-info/WHEEL
cloud_array-0.0.7.dist-info/top_level.txt
cloud_array-0.0.7.dist-info/RECORD
