Metadata-Version: 2.1
Name: cloud-array
Version: 0.0.7
Summary: Cloud implementation of array for Big Data
Home-page: https://github.com/micmurawski/cloud-array/
Author: Michal Murawski
Author-email: mmurawski777@gmail.com
License: MIT
Platform: UNKNOWN
Classifier: License :: OSI Approved :: MIT License
Classifier: Programming Language :: Python :: 3
Classifier: Programming Language :: Python :: 3.6
Classifier: Programming Language :: Python :: 3.7
Classifier: Programming Language :: Python :: 3.8
Requires-Python: >=3.7,<4.0
License-File: LICENSE
Requires-Dist: numpy
